go_patch_it/__init__.py
go_patch_it/apply.py
go_patch_it/cli.py
go_patch_it/generate.py
go_patch_it/core/__init__.py
go_patch_it/core/cache.py
go_patch_it/core/files.py
go_patch_it/core/git.py
go_patch_it/core/output.py
go_patch_it/core/package_manager.py
go_patch_it/core/processing.py
go_patch_it/managers/__init__.py
go_patch_it/managers/base.py
go_patch_it/managers/go.py
go_patch_it/managers/npm_yarn.py
go_patch_it-0.1.2.dist-info/METADATA
go_patch_it-0.1.2.dist-info/WHEEL
go_patch_it-0.1.2.dist-info/entry_points.txt
go_patch_it-0.1.2.dist-info/licenses/LICENSE
go_patch_it-0.1.2.dist-info/RECORD
