Metadata-Version: 2.4
Name: go-patch-it
Version: 0.1.2
Summary: A tool to automatically find and apply patch version upgrades for Go modules and npm/yarn packages
Author: William Grochocinski
License: MIT
License-File: LICENSE
Keywords: go,golang,modules,npm,package,patch,upgrade,version,yarn
Classifier: Development Status :: 4 - Beta
Classifier: Intended Audience :: Developers
Classifier: License :: OSI Approved :: MIT License
Classifier: Programming Language :: Python :: 3
Classifier: Programming Language :: Python :: 3.8
Classifier: Programming Language :: Python :: 3.9
Classifier: Programming Language :: Python :: 3.10
Classifier: Programming Language :: Python :: 3.11
Classifier: Programming Language :: Python :: 3.12
Classifier: Programming Language :: Python :: 3.13
Classifier: Programming Language :: Python :: 3.14
Classifier: Topic :: Software Development :: Build Tools
Classifier: Topic :: Software Development :: Libraries :: Python Modules
Requires-Python: >=3.8
